{
  "name": "Transparent NPC Wall for Links",
  "description": "An invisible wall that blocks links from passing through.",
  "InternalName": "リンク用透明NPC壁",
  "category": "Object",
  "fields": [
    {
      "name": "Activation Variable",
      "description": "The local variable that triggers or activates this actor. (0 = always active)",
      "bitOffset": 27,
      "bitSize": 5,
      "valueType": "Integer"
    },
    {
      "name": "Horizontal Length",
      "description": "The horizontal length of the transparent NPC wall.",
      "bitOffset": 8,
      "bitSize": 8,
      "valueType": "Integer"
    },
    {
      "name": "Vertical Length",
      "description": "The vertical length of the transparent NPC wall.",
      "bitOffset": 0,
      "bitSize": 8,
      "valueType": "Integer"
    }
  ]
}
